Workbook
Name aporte: INVESTIMENTOS!$D$16
Name patrimonio: INVESTIMENTOS!$D$19
Name qtd_anos: INVESTIMENTOS!$D$17
Name rendimento_carteira: INVESTIMENTOS!$D$12
Name rendimento_mensal: INVESTIMENTOS!$D$18
Name salario: INVESTIMENTOS!$D$11
Name sugestao_investimento: INVESTIMENTOS!$D$13

Sheet INVESTIMENTOS
B10: CONFIGURAÇÕES
B11: Salário | D11: 2700
B12: Rendimento da Carteira | D12: 0.008
B13: Sugestão de investimento (30%) | D13: =D11*30% -> 810
B15: INVESTIMENTO MENSAL
B16: QUANTO INVESTIR POR MÊS ? | D16: 810
B17: POR QUANTOS ANOS ? | D17: 5
B18: TAXA DE RENDIMENTO MENSAL ? | D18: 0.01078
B19: PATRIMÔNIO ACUMULADO ? | D19: =FV(rendimento_mensal,qtd_anos*12,aporte*-1) -> 67837.354
B20: DIVIDENDOS MENSAIS ? | D20: =patrimonio*rendimento_carteira -> 542.69883
B22: Cenários | D22: Dividendos
A23: 2 | B23: Quanto em 2 anos ? | C23: =FV(rendimento_mensal,A23*12,aporte*-1) -> 22051.757 | D23: =C23*rendimento_carteira -> 176.41406
A24: 5 | B24: Quanto em 5 anos ? | C24: =FV(rendimento_mensal,A24*12,aporte*-1) -> 67837.354 | D24: =C24*rendimento_carteira -> 542.69883
A25: 10 | B25: Quanto em 10 anos ? | C25: =FV(rendimento_mensal,A25*12,aporte*-1) -> 196919.83 | D25: =C25*rendimento_carteira -> 1575.3587
A26: 20 | B26: Quanto em 20 anos ? | C26: =FV(rendimento_mensal,A26*12,aporte*-1) -> 909914.49 | D26: =C26*rendimento_carteira -> 7279.3159
B28: PERFIL | C28: Agressivo
B29: VALORE A SER INVESTIDO POR MÊS | C29: =aporte -> 810
B31: TIPOS DE FIIS
B32: PAPEL | C32: =VLOOKUP($C$28&"-"&B32,PERF_INVS!$A$2:$D$19,4,FALSE) -> 0.5 | D32: =C32*aporte -> 405
B33: TIJOLO | C33: =VLOOKUP($C$28&"-"&B33,PERF_INVS!$A$2:$D$19,4,FALSE) -> 0.1 | D33: =C33*aporte -> 81
B34: HÍBRIDO | C34: =VLOOKUP($C$28&"-"&B34,PERF_INVS!$A$2:$D$19,4,FALSE) -> 0.1 | D34: =C34*aporte -> 81
B35: FOFs | C35: =VLOOKUP($C$28&"-"&B35,PERF_INVS!$A$2:$D$19,4,FALSE) -> 0.05 | D35: =C35*aporte -> 40.5
B36: DESENVOLVIMENTO | C36: =VLOOKUP($C$28&"-"&B36,PERF_INVS!$A$2:$D$19,4,FALSE) -> 0.2 | D36: =C36*aporte -> 162
B37: HOTELARIA | C37: =VLOOKUP($C$28&"-"&B37,PERF_INVS!$A$2:$D$19,4,FALSE) -> 0.05 | D37: =C37*aporte -> 40.5
D38: =SUM(D32:D37) -> 810

Sheet PERF_INVS
A1: CHAVE | B1: PERFIL | C1: TIPO | D1: %
A2: =B2&"-"&C2 -> Conservador-PAPEL | B2: Conservador | C2: PAPEL | D2: 0.3
A3: =B3&"-"&C3 -> Conservador-TIJOLO | B3: Conservador | C3: TIJOLO | D3: 0.5
A4: =B4&"-"&C4 -> Conservador-HÍBRIDO | B4: Conservador | C4: HÍBRIDO | D4: 0.1
A5: =B5&"-"&C5 -> Conservador-FOFs | B5: Conservador | C5: FOFs | D5: 0.1
A6: =B6&"-"&C6 -> Conservador-DESENVOLVIMENTO | B6: Conservador | C6: DESENVOLVIMENTO | D6: 0
A7: =B7&"-"&C7 -> Conservador-HOTELARIA | B7: Conservador | C7: HOTELARIA | D7: 0
A8: =B8&"-"&C8 -> Moderado-PAPEL | B8: Moderado | C8: PAPEL | D8: 0.32
A9: =B9&"-"&C9 -> Moderado-TIJOLO | B9: Moderado | C9: TIJOLO | D9: 0.4
A10: =B10&"-"&C10 -> Moderado-HÍBRIDO | B10: Moderado | C10: HÍBRIDO | D10: 0.08
A11: =B11&"-"&C11 -> Moderado-FOFs | B11: Moderado | C11: FOFs | D11: 0.1
A12: =B12&"-"&C12 -> Moderado-DESENVOLVIMENTO | B12: Moderado | C12: DESENVOLVIMENTO | D12: 0.1
A13: =B13&"-"&C13 -> Moderado-HOTELARIA | B13: Moderado | C13: HOTELARIA | D13: 0
... A19: =B19&"-"&C19 -> Agressivo-HOTELARIA | B19: Agressivo | C19: HOTELARIA | D19: 0.05
